{

"Football": [


    {
    "EventImage" : "file:///android_asset/cricket.png",
    "EventName" : "UEFA",
  "Url" : "https://crik.live/Football_Channels.json"
  },
    {
    "EventImage" : "file:///android_asset/cricket.png",
    "EventName" : "Sky Sports Main Event",
  "Url" : "https://crik.live/Football_Channels.json"
  },
    {
    "EventImage" : "file:///android_asset/cricket.png",
    "EventName" : "Sky Sports Football",
  "Url" : "https://crik.live/Football_Channels.json"
  },
    {
    "EventImage" : "file:///android_asset/cricket.png",
    "EventName" : "Ten Sports",
  "Url" : "https://crik.live/Football_Channels.json"
  }
]
}
